vzlog/__init__.py
vzlog/default.py
vzlog/pyplot.py
vzlog/vzlog.py
vzlog/image/__init__.py
vzlog/image/color_image_grid.py
vzlog/image/image_grid.py
vzlog/image/resample.so
vzlog/img/resample.so
vzlog-0.1.8.dist-info/DESCRIPTION.rst
vzlog-0.1.8.dist-info/METADATA
vzlog-0.1.8.dist-info/metadata.json
vzlog-0.1.8.dist-info/RECORD
vzlog-0.1.8.dist-info/top_level.txt
vzlog-0.1.8.dist-info/WHEEL
