Metadata-Version: 2.0
Name: vzlog
Version: 0.1.8
Summary: Python tool for logging rich content, particularly plots and images
Home-page: https://github.com/gustavla/vzlog
Author: Gustav Larsson
Author-email: gustav.m.larsson@gmail.com
License: BSD
Platform: UNKNOWN
Classifier: Development Status :: 2 - Pre-Alpha
Classifier: Intended Audience :: Science/Research
Classifier: Intended Audience :: Developers
Classifier: License :: OSI Approved :: BSD License
Classifier: Programming Language :: Python
Classifier: Programming Language :: Python :: 2
Classifier: Programming Language :: Python :: 3
Requires-Dist: numpy
Requires-Dist: cython
Requires-Dist: scipy
Requires-Dist: matplotlib
Requires-Dist: Pillow
Requires-Dist: scikit-image
